peakrdl_pyuvm/__init__.py
peakrdl_pyuvm/__peakrdl__.py
peakrdl_pyuvm/exporter.py
peakrdl_pyuvm/hello.py
peakrdl_pyuvm/pre_export_listener.py
peakrdl_pyuvm/templates/init.py.j2
peakrdl_pyuvm/templates/main.j2
peakrdl_pyuvm/templates/utils.j2
peakrdl_pyuvm/templates/uvm_reg.py.j2
peakrdl_pyuvm/templates/uvm_reg_block-mem.py.j2
peakrdl_pyuvm/templates/uvm_reg_block.py.j2
peakrdl_pyuvm/templates/uvm_vreg.py.j2
peakrdl_pyuvm-0.1.1.dist-info/licenses/LICENSE
peakrdl_pyuvm-0.1.1.dist-info/METADATA
peakrdl_pyuvm-0.1.1.dist-info/WHEEL
peakrdl_pyuvm-0.1.1.dist-info/entry_points.txt
peakrdl_pyuvm-0.1.1.dist-info/top_level.txt
peakrdl_pyuvm-0.1.1.dist-info/RECORD
