Metadata-Version: 2.4
Name: peakrdl-pyuvm
Version: 0.1.1
Summary: Generate pyuvm register model from SystemRDL
Author-email: Rasmus Grøndahl Olsen <simplhdl@gmail.com>
Maintainer-email: Rasmus Grøndahl Olsen <simplhdl@gmail.com>
License: MIT License
Project-URL: Source, https://github.com/RasmusGOlsen/peakrdl-pyuvm
Project-URL: Tracker, https://github.com/RasmusGOlsen/peakrdl-pyuvm/issues
Project-URL: Changelog, https://github.com/RasmusGOlsen/peakrdl-pyuvm/releases
Classifier: Development Status :: 4 - Beta
Classifier: Programming Language :: Python :: 3
Classifier: Programming Language :: Python :: 3.7
Classifier: Programming Language :: Python :: 3.8
Classifier: Programming Language :: Python :: 3.9
Classifier: Programming Language :: Python :: 3.10
Classifier: Programming Language :: Python :: 3.11
Classifier: Programming Language :: Python :: 3.12
Classifier: Programming Language :: Python :: 3.13
Classifier: Intended Audience :: Developers
Classifier: License :: OSI Approved :: MIT License
Classifier: Topic :: Scientific/Engineering :: Electronic Design Automation (EDA)
Classifier: Operating System :: OS Independent
Requires-Python: >=3.7
License-File: LICENSE
Requires-Dist: systemrdl-compiler
Requires-Dist: jinja2
Requires-Dist: numpy
Dynamic: license-file
